pilottai_tools/__init__.py
pilottai_tools/tools.py
pilottai_tools/config/model.py
pilottai_tools/memory/__init__.py
pilottai_tools/memory/memory.py
pilottai_tools/memory/elasticsearch/elasticsearch.py
pilottai_tools/memory/graph/graph.py
pilottai_tools/memory/mongo/__init__.py
pilottai_tools/memory/mysql/__init__.py
pilottai_tools/memory/postgres/__init__.py
pilottai_tools/memory/redis/__init__.py
pilottai_tools/memory/redis/client.py
pilottai_tools/memory/redis/config.py
pilottai_tools/memory/redis/publisher.py
pilottai_tools/memory/sqllite/__init__.py
pilottai_tools/source/__init__.py
pilottai_tools/source/knowledge.py
pilottai_tools/source/base/__init__.py
pilottai_tools/source/base/audio_input.py
pilottai_tools/source/base/base_input.py
pilottai_tools/source/base/doc_input.py
pilottai_tools/source/base/image_input.py
pilottai_tools/source/base/json_input.py
pilottai_tools/source/base/markup_input.py
pilottai_tools/source/base/stream_input.py
pilottai_tools/source/base/string_input.py
pilottai_tools/source/base/structured_input.py
pilottai_tools/source/base/url_input.py
pilottai_tools/source/base/vector_input.py
pilottai_tools/source/base/video_input.py
pilottai_tools/source/base/webscrapper.py
pilottai_tools/utils/__init__.py
pilottai_tools/utils/formatter.py
pilottai_tools/utils/logger.py
pilottai_tools/vectorstore/chromadb/__init__.py
pilottai_tools/vectorstore/faiss/__init__.py
pilottai_tools/vectorstore/milvus/__init__.py
pilottai_tools-0.1.0.dist-info/METADATA
pilottai_tools-0.1.0.dist-info/WHEEL
pilottai_tools-0.1.0.dist-info/licenses/LICENSE
pilottai_tools-0.1.0.dist-info/RECORD
